[
    {
        "n": "10",
        "k": "3",
        "time": 0.23594004399978985,
        "n_processos": 4,
        "tempo_tela": 15
    },
    {
        "n": "10",
        "k": "4",
        "time": 0.2014025749999746,
        "n_processos": 5,
        "tempo_tela": 18
    },
    {
        "n": "10",
        "k": "6",
        "time": 0.20546586000000389,
        "n_processos": 5,
        "tempo_tela": 13
    },
    {
        "n": "10",
        "k": "8",
        "time": 0.2031257490000371,
        "n_processos": 5,
        "tempo_tela": 16
    },
    {
        "n": "10",
        "k": "10",
        "time": 0.19958597799995914,
        "n_processos": 4,
        "tempo_tela": 13
    },
    {
        "n": "20",
        "k": "3",
        "time": 0.1975488220000443,
        "n_processos": 6,
        "tempo_tela": 19
    },
    {
        "n": "20",
        "k": "4",
        "time": 0.19833862699988458,
        "n_processos": 6,
        "tempo_tela": 18
    },
    {
        "n": "20",
        "k": "6",
        "time": 0.2061116800000491,
        "n_processos": 6,
        "tempo_tela": 18
    },
    {
        "n": "20",
        "k": "8",
        "time": 0.2083444380000401,
        "n_processos": 6,
        "tempo_tela": 16
    },
    {
        "n": "20",
        "k": "10",
        "time": 0.19801454899993587,
        "n_processos": 6,
        "tempo_tela": 17
    },
    {
        "n": "25",
        "k": "3",
        "time": 0.20760639100012668,
        "n_processos": 5,
        "tempo_tela": 20
    },
    {
        "n": "25",
        "k": "4",
        "time": 0.21274548699989282,
        "n_processos": 6,
        "tempo_tela": 19
    },
    {
        "n": "25",
        "k": "6",
        "time": 0.21277773699989666,
        "n_processos": 7,
        "tempo_tela": 23
    },
    {
        "n": "25",
        "k": "8",
        "time": 0.21247961499989287,
        "n_processos": 6,
        "tempo_tela": 18
    },
    {
        "n": "25",
        "k": "10",
        "time": 0.21697196599984636,
        "n_processos": 6,
        "tempo_tela": 18
    },
    {
        "n": "30",
        "k": "3",
        "time": 0.5653336059999674,
        "n_processos": 6,
        "tempo_tela": 16
    },
    {
        "n": "30",
        "k": "4",
        "time": 0.4640361199999461,
        "n_processos": 7,
        "tempo_tela": 18
    },
    {
        "n": "30",
        "k": "6",
        "time": 0.4576513930001056,
        "n_processos": 6,
        "tempo_tela": 19
    },
    {
        "n": "30",
        "k": "8",
        "time": 0.4516898859999401,
        "n_processos": 7,
        "tempo_tela": 23
    },
    {
        "n": "30",
        "k": "10",
        "time": 0.45275394700001925,
        "n_processos": 6,
        "tempo_tela": 19
    }
]